django_utils/__init__.py
django_utils/consumers.py
django_utils/exceptions.py
django_utils/fields.py
django_utils/filters.py
django_utils/jwt_utils.py
django_utils/mock_request.py
django_utils/pagination.py
django_utils/parsers.py
django_utils/permissions.py
django_utils/serializers.py
django_utils/utils.py
django_utils/views.py
django_utils/migrations/__init__.py
samsteady_django_utils-1.0.30.dist-info/METADATA
samsteady_django_utils-1.0.30.dist-info/WHEEL
samsteady_django_utils-1.0.30.dist-info/top_level.txt
samsteady_django_utils-1.0.30.dist-info/RECORD
