Metadata-Version: 2.1
Name: samsteady-django-utils
Version: 1.0.30
Summary: Django utils
License: MIT
Classifier: Development Status :: 4 - Beta
Classifier: Environment :: Web Environment
Classifier: Intended Audience :: Developers
Classifier: License :: OSI Approved :: MIT License
Classifier: Operating System :: OS Independent
Classifier: Programming Language :: Python :: 3 :: Only
Classifier: Programming Language :: Python :: 3.7
Classifier: Programming Language :: Python :: Implementation :: CPython
Classifier: Topic :: Software Development :: Libraries :: Application Frameworks
Classifier: Topic :: Software Development :: Libraries :: Python Modules
Requires-Python: >=3.6
Requires-Dist: django (>=3.0)
Requires-Dist: djangorestframework (>=3.7)
Requires-Dist: jsonfield (>=3.1.0)
Requires-Dist: dj-rest-auth (>=2.2.3)
Requires-Dist: channels (>=3.0.5)
Requires-Dist: django-filter (>=2.4.0)
